{
  "main": {
    "id": "b9108b12a782fd68",
    "type": "split",
    "children": [
      {
        "id": "09dbabcfb6f76b59",
        "type": "tabs",
        "children": [
          {
            "id": "65d3db0bb18bf298",
            "type": "leaf",
            "state": {
              "type": "markdown",
              "state": {
                "file": "图片/web常用图片格式及实践分享.md",
                "mode": "preview",
                "source": false
              }
            }
          }
        ]
      }
    ],
    "direction": "vertical"
  },
  "left": {
    "id": "14399cbbfce9eea0",
    "type": "split",
    "children": [
      {
        "id": "b69d55e13261e4c5",
        "type": "tabs",
        "children": [
          {
            "id": "19ea864b7684327e",
            "type": "leaf",
            "state": {
              "type": "file-explorer",
              "state": {
                "sortOrder": "alphabetical"
              }
            }
          },
          {
            "id": "52567858603acd4b",
            "type": "leaf",
            "state": {
              "type": "search",
              "state": {
                "query": "",
                "matchingCase": false,
                "explainSearch": false,
                "collapseAll": false,
                "extraContext": false,
                "sortOrder": "alphabetical"
              }
            }
          },
          {
            "id": "ac2f123e9d51f3d1",
            "type": "leaf",
            "state": {
              "type": "starred",
              "state": {}
            }
          }
        ]
      }
    ],
    "direction": "horizontal",
    "width": 300
  },
  "right": {
    "id": "cb43aee902ac5afe",
    "type": "split",
    "children": [
      {
        "id": "2f1272d1f4cd244f",
        "type": "tabs",
        "children": [
          {
            "id": "e1a4179e893f69d3",
            "type": "leaf",
            "state": {
              "type": "backlink",
              "state": {
                "file": "图片/web常用图片格式及实践分享.md",
                "collapseAll": false,
                "extraContext": false,
                "sortOrder": "alphabetical",
                "showSearch": false,
                "searchQuery": "",
                "backlinkCollapsed": false,
                "unlinkedCollapsed": true
              }
            }
          },
          {
            "id": "c11040de08b8c52c",
            "type": "leaf",
            "state": {
              "type": "outgoing-link",
              "state": {
                "file": "图片/web常用图片格式及实践分享.md",
                "linksCollapsed": false,
                "unlinkedCollapsed": true
              }
            }
          },
          {
            "id": "518c54126a821d47",
            "type": "leaf",
            "state": {
              "type": "tag",
              "state": {
                "sortOrder": "frequency",
                "useHierarchy": true
              }
            }
          },
          {
            "id": "d621f0357b019667",
            "type": "leaf",
            "state": {
              "type": "outline",
              "state": {
                "file": "图片/web常用图片格式及实践分享.md"
              }
            }
          },
          {
            "id": "c11b92ee768d2d14",
            "type": "leaf",
            "state": {
              "type": "advanced-tables-toolbar",
              "state": {}
            }
          }
        ],
        "currentTab": 3
      }
    ],
    "direction": "horizontal",
    "width": 321.5
  },
  "active": "65d3db0bb18bf298",
  "lastOpenFiles": [
    "Ding.md",
    "2022-11-25.md",
    "未命名.md",
    "图片/web常用图片格式及实践分享.md",
    "2022-11-22.md",
    "性能/图片性能.md",
    "webpack构建工具/webpack流程.md",
    "_assets/image-1627617460200.png",
    "_assets/20220320224355.png",
    "_assets/20220320214422.png"
  ]
}